dataplug/__init__.py
dataplug/api.py
dataplug/client.py
dataplug/edge.py
dataplug/graph.py
dataplug/node.py
dataplug/utils.py
dataplug-3.0.2.dist-info/LICENSE
dataplug-3.0.2.dist-info/METADATA
dataplug-3.0.2.dist-info/WHEEL
dataplug-3.0.2.dist-info/top_level.txt
dataplug-3.0.2.dist-info/RECORD
