Metadata-Version: 2.1
Name: dataplug
Version: 3.0.2
Summary: Schemaless, NoSQL, multi-model data interactions on top ArangoDB
Home-page: https://github.com/redsharpbyte/dataplug
Author: Red Boumghar
License: MIT
Keywords: schemaless,no-sql,multi-model,data,graph,databasea
Platform: UNKNOWN
Classifier: Intended Audience :: Developers
Classifier: Programming Language :: Python :: 3
Classifier: License :: OSI Approved :: MIT License
Requires-Python: >=3
License-File: LICENSE
Requires-Dist: python-arango
Provides-Extra: test
Requires-Dist: pytest ; extra == 'test'
